{"paging": {"pageIndex": 1, "pageSize": 500, "total": 24}, "baseComponent": {"id": "AXhG14ZOfXuIojY5gzXQ", "key": "fga-eps-mds_2020-2-G4-Demands", "name": "2020-2-SiGeD-Demands", "qualifier": "TRK", "measures": [{"metric": "duplicated_lines_density", "value": "0.0", "bestValue": true}, {"metric": "functions", "value": "66"}, {"metric": "security_rating", "value": "1.0", "bestValue": true}, {"metric": "files", "value": "17"}, {"metric": "complexity", "value": "138"}, {"metric": "ncloc", "value": "1125"}, {"metric": "coverage", "value": "90.3", "bestValue": false}, {"metric": "reliability_rating", "value": "1.0", "bestValue": true}, {"metric": "comment_lines_density", "value": "0.0", "bestValue": false}]}, "components": [{"id": "AXklrzLaWhg0fzn4kIj5", "key": "fga-eps-mds_2020-2-G4-Demands:src/Controllers/AlertController.js", "name": "AlertController.js", "qualifier": "FIL", "path": "src/Controllers/AlertController.js", "language": "js", "measures": [{"metric": "functions", "value": "6"}, {"metric": "security_rating", "value": "1.0", "bestValue": true}, {"metric": "files", "value": "1"}, {"metric": "complexity", "value": "11"}, {"metric": "ncloc", "value": "72"}, {"metric": "coverage", "value": "86.5", "bestValue": false}, {"metric": "reliability_rating", "value": "1.0", "bestValue": true}, {"metric": "comment_lines_density", "value": "0.0", "bestValue": false}, {"metric": "duplicated_lines_density", "value": "0.0", "bestValue": true}, {"metric": "test_success_density", "value": "100.0", "bestValue": true}]}, {"id": "AXklrzLaWhg0fzn4kIj6", "key": "fga-eps-mds_2020-2-G4-Demands:src/Models/AlertSchema.js", "name": "AlertSchema.js", "qualifier": "FIL", "path": "src/Models/AlertSchema.js", "language": "js", "measures": [{"metric": "complexity", "value": "0"}, {"metric": "functions", "value": "0"}, {"metric": "ncloc", "value": "37"}, {"metric": "coverage", "value": "100.0", "bestValue": true}, {"metric": "reliability_rating", "value": "1.0", "bestValue": true}, {"metric": "security_rating", "value": "1.0", "bestValue": true}, {"metric": "comment_lines_density", "value": "0.0", "bestValue": false}, {"metric": "files", "value": "1"}, {"metric": "duplicated_lines_density", "value": "0.0", "bestValue": true}, {"metric": "test_success_density", "value": "100.0", "bestValue": true}]}, {"id": "AXkeJgjjaPZPm53PKkdK", "key": "fga-eps-mds_2020-2-G4-Demands:tests/__mocks__/axios.js", "name": "axios.js", "qualifier": "FIL", "path": "tests/__mocks__/axios.js", "language": "js", "measures": [{"metric": "complexity", "value": "5"}, {"metric": "functions", "value": "2"}, {"metric": "ncloc", "value": "21"}, {"metric": "reliability_rating", "value": "1.0", "bestValue": true}, {"metric": "security_rating", "value": "1.0", "bestValue": true}, {"metric": "comment_lines_density", "value": "0.0", "bestValue": false}, {"metric": "files", "value": "1"}, {"metric": "duplicated_lines_density", "value": "0.0", "bestValue": true}, {"metric": "test_success_density", "value": "100.0", "bestValue": true}]}, {"id": "AXkeJgjjaPZPm53PKkdP", "key": "fga-eps-mds_2020-2-G4-Demands:src/Services/Axios/baseService.js", "name": "baseService.js", "qualifier": "FIL", "path": "src/Services/Axios/baseService.js", "language": "js", "measures": [{"metric": "complexity", "value": "0"}, {"metric": "functions", "value": "0"}, {"metric": "ncloc", "value": "12"}, {"metric": "coverage", "value": "100.0", "bestValue": true}, {"metric": "reliability_rating", "value": "1.0", "bestValue": true}, {"metric": "security_rating", "value": "1.0", "bestValue": true}, {"metric": "comment_lines_density", "value": "0.0", "bestValue": false}, {"metric": "files", "value": "1"}, {"metric": "duplicated_lines_density", "value": "0.0", "bestValue": true}, {"metric": "test_success_density", "value": "100.0", "bestValue": true}]}, {"id": "AXhhCSPPVrchjitanYAi", "key": "fga-eps-mds_2020-2-G4-Demands:src/Controllers/CategoryController.js", "name": "CategoryController.js", "qualifier": "FIL", "path": "src/Controllers/CategoryController.js", "language": "js", "measures": [{"metric": "functions", "value": "6"}, {"metric": "security_rating", "value": "1.0", "bestValue": true}, {"metric": "files", "value": "1"}, {"metric": "complexity", "value": "8"}, {"metric": "ncloc", "value": "62"}, {"metric": "coverage", "value": "100.0", "bestValue": true}, {"metric": "reliability_rating", "value": "1.0", "bestValue": true}, {"metric": "comment_lines_density", "value": "0.0", "bestValue": false}, {"metric": "duplicated_lines_density", "value": "0.0", "bestValue": true}, {"metric": "test_success_density", "value": "100.0", "bestValue": true}]}, {"id": "AXhhCSPPVrchjitanYAk", "key": "fga-eps-mds_2020-2-G4-Demands:src/Models/CategorySchema.js", "name": "CategorySchema.js", "qualifier": "FIL", "path": "src/Models/CategorySchema.js", "language": "js", "measures": [{"metric": "complexity", "value": "0"}, {"metric": "functions", "value": "0"}, {"metric": "ncloc", "value": "24"}, {"metric": "coverage", "value": "100.0", "bestValue": true}, {"metric": "reliability_rating", "value": "1.0", "bestValue": true}, {"metric": "security_rating", "value": "1.0", "bestValue": true}, {"metric": "comment_lines_density", "value": "0.0", "bestValue": false}, {"metric": "files", "value": "1"}, {"metric": "duplicated_lines_density", "value": "0.0", "bestValue": true}, {"metric": "test_success_density", "value": "100.0", "bestValue": true}]}, {"id": "AXkeJgjjaPZPm53PKkdQ", "key": "fga-eps-mds_2020-2-G4-Demands:src/Services/Axios/clientService.js", "name": "clientService.js", "qualifier": "FIL", "path": "src/Services/Axios/clientService.js", "language": "js", "measures": [{"metric": "functions", "value": "2"}, {"metric": "security_rating", "value": "1.0", "bestValue": true}, {"metric": "files", "value": "1"}, {"metric": "complexity", "value": "2"}, {"metric": "ncloc", "value": "14"}, {"metric": "coverage", "value": "77.8", "bestValue": false}, {"metric": "reliability_rating", "value": "1.0", "bestValue": true}, {"metric": "comment_lines_density", "value": "0.0", "bestValue": false}, {"metric": "duplicated_lines_density", "value": "0.0", "bestValue": true}, {"metric": "test_success_density", "value": "100.0", "bestValue": true}]}, {"id": "AXkk61nHGsI8ClE_MzUW", "key": "fga-eps-mds_2020-2-G4-Demands:scripts/consts.js", "name": "consts.js", "qualifier": "FIL", "path": "scripts/consts.js", "language": "js", "measures": [{"metric": "complexity", "value": "0"}, {"metric": "functions", "value": "0"}, {"metric": "ncloc", "value": "9"}, {"metric": "reliability_rating", "value": "1.0", "bestValue": true}, {"metric": "security_rating", "value": "1.0", "bestValue": true}, {"metric": "comment_lines_density", "value": "0.0", "bestValue": false}, {"metric": "files", "value": "1"}, {"metric": "duplicated_lines_density", "value": "0.0", "bestValue": true}, {"metric": "test_success_density", "value": "100.0", "bestValue": true}]}, {"id": "AXhhCSPPVrchjitanYAj", "key": "fga-eps-mds_2020-2-G4-Demands:src/Controllers", "name": "Controllers", "qualifier": "DIR", "path": "src/Controllers", "measures": [{"metric": "duplicated_lines_density", "value": "0.0", "bestValue": true}, {"metric": "functions", "value": "37"}, {"metric": "security_rating", "value": "1.0", "bestValue": true}, {"metric": "files", "value": "3"}, {"metric": "complexity", "value": "72"}, {"metric": "ncloc", "value": "609"}, {"metric": "coverage", "value": "89.8", "bestValue": false}, {"metric": "reliability_rating", "value": "1.0", "bestValue": true}, {"metric": "comment_lines_density", "value": "0.0", "bestValue": false}]}, {"id": "AXjQ2UpTUquo9QSM1Ax6", "key": "fga-eps-mds_2020-2-G4-Demands:src/Controllers/DemandController.js", "name": "DemandController.js", "qualifier": "FIL", "path": "src/Controllers/DemandController.js", "language": "js", "measures": [{"metric": "functions", "value": "25"}, {"metric": "security_rating", "value": "1.0", "bestValue": true}, {"metric": "files", "value": "1"}, {"metric": "complexity", "value": "53"}, {"metric": "ncloc", "value": "475"}, {"metric": "coverage", "value": "88.8", "bestValue": false}, {"metric": "reliability_rating", "value": "1.0", "bestValue": true}, {"metric": "comment_lines_density", "value": "0.0", "bestValue": false}, {"metric": "duplicated_lines_density", "value": "0.0", "bestValue": true}, {"metric": "test_success_density", "value": "100.0", "bestValue": true}]}, {"id": "AXjQ2UpTUquo9QSM1Ax7", "key": "fga-eps-mds_2020-2-G4-Demands:src/Models/DemandSchema.js", "name": "DemandSchema.js", "qualifier": "FIL", "path": "src/Models/DemandSchema.js", "language": "js", "measures": [{"metric": "complexity", "value": "0"}, {"metric": "functions", "value": "0"}, {"metric": "ncloc", "value": "115"}, {"metric": "coverage", "value": "100.0", "bestValue": true}, {"metric": "reliability_rating", "value": "1.0", "bestValue": true}, {"metric": "security_rating", "value": "1.0", "bestValue": true}, {"metric": "comment_lines_density", "value": "0.0", "bestValue": false}, {"metric": "files", "value": "1"}, {"metric": "duplicated_lines_density", "value": "0.0", "bestValue": true}, {"metric": "test_success_density", "value": "100.0", "bestValue": true}]}, {"id": "AXkeJgjjaPZPm53PKkdN", "key": "fga-eps-mds_2020-2-G4-Demands:src/Utils/functionsJWT.js", "name": "functionsJWT.js", "qualifier": "FIL", "path": "src/Utils/functionsJWT.js", "language": "js", "measures": [{"metric": "complexity", "value": "4"}, {"metric": "functions", "value": "2"}, {"metric": "ncloc", "value": "16"}, {"metric": "reliability_rating", "value": "1.0", "bestValue": true}, {"metric": "security_rating", "value": "1.0", "bestValue": true}, {"metric": "comment_lines_density", "value": "0.0", "bestValue": false}, {"metric": "files", "value": "1"}, {"metric": "duplicated_lines_density", "value": "0.0", "bestValue": true}, {"metric": "test_success_density", "value": "100.0", "bestValue": true}]}, {"id": "AXhhCSPPVrchjitanYAh", "key": "fga-eps-mds_2020-2-G4-Demands:src/index.js", "name": "index.js", "qualifier": "FIL", "path": "src/index.js", "language": "js", "measures": [{"metric": "complexity", "value": "3"}, {"metric": "functions", "value": "3"}, {"metric": "ncloc", "value": "28"}, {"metric": "coverage", "value": "94.1", "bestValue": false}, {"metric": "reliability_rating", "value": "1.0", "bestValue": true}, {"metric": "security_rating", "value": "1.0", "bestValue": true}, {"metric": "comment_lines_density", "value": "0.0", "bestValue": false}, {"metric": "files", "value": "1"}, {"metric": "duplicated_lines_density", "value": "0.0", "bestValue": true}, {"metric": "test_success_density", "value": "100.0", "bestValue": true}]}, {"id": "AXhhCSPPVrchjitanYAl", "key": "fga-eps-mds_2020-2-G4-Demands:src/Models", "name": "Models", "qualifier": "DIR", "path": "src/Models", "measures": [{"metric": "duplicated_lines_density", "value": "0.0", "bestValue": true}, {"metric": "functions", "value": "0"}, {"metric": "security_rating", "value": "1.0", "bestValue": true}, {"metric": "files", "value": "3"}, {"metric": "complexity", "value": "0"}, {"metric": "ncloc", "value": "176"}, {"metric": "coverage", "value": "100.0", "bestValue": true}, {"metric": "reliability_rating", "value": "1.0", "bestValue": true}, {"metric": "comment_lines_density", "value": "0.0", "bestValue": false}]}, {"id": "AXjQ2UpTUquo9QSM1Ax_", "key": "fga-eps-mds_2020-2-G4-Demands:scripts/release.js", "name": "release.js", "qualifier": "FIL", "path": "scripts/release.js", "language": "js", "measures": [{"metric": "complexity", "value": "8"}, {"metric": "functions", "value": "7"}, {"metric": "ncloc", "value": "60"}, {"metric": "reliability_rating", "value": "1.0", "bestValue": true}, {"metric": "security_rating", "value": "1.0", "bestValue": true}, {"metric": "comment_lines_density", "value": "0.0", "bestValue": false}, {"metric": "files", "value": "1"}, {"metric": "duplicated_lines_density", "value": "0.0", "bestValue": true}, {"metric": "test_success_density", "value": "100.0", "bestValue": true}]}, {"id": "AXhhCSPPVrchjitanYAm", "key": "fga-eps-mds_2020-2-G4-Demands:src/routes.js", "name": "routes.js", "qualifier": "FIL", "path": "src/routes.js", "language": "js", "measures": [{"metric": "complexity", "value": "0"}, {"metric": "functions", "value": "0"}, {"metric": "ncloc", "value": "30"}, {"metric": "coverage", "value": "100.0", "bestValue": true}, {"metric": "reliability_rating", "value": "1.0", "bestValue": true}, {"metric": "security_rating", "value": "1.0", "bestValue": true}, {"metric": "comment_lines_density", "value": "0.0", "bestValue": false}, {"metric": "files", "value": "1"}, {"metric": "duplicated_lines_density", "value": "0.0", "bestValue": true}, {"metric": "test_success_density", "value": "100.0", "bestValue": true}]}, {"id": "AXjQ2UpTUquo9QSM1AyA", "key": "fga-eps-mds_2020-2-G4-Demands:scripts", "name": "scripts", "qualifier": "DIR", "path": "scripts", "measures": [{"metric": "duplicated_lines_density", "value": "0.0", "bestValue": true}, {"metric": "functions", "value": "7"}, {"metric": "security_rating", "value": "1.0", "bestValue": true}, {"metric": "files", "value": "2"}, {"metric": "complexity", "value": "8"}, {"metric": "ncloc", "value": "69"}, {"metric": "reliability_rating", "value": "1.0", "bestValue": true}, {"metric": "comment_lines_density", "value": "0.0", "bestValue": false}]}, {"id": "AXkeJgjjaPZPm53PKkdR", "key": "fga-eps-mds_2020-2-G4-Demands:src/Services/Axios", "name": "Services/Axios", "qualifier": "DIR", "path": "src/Services/Axios", "measures": [{"metric": "duplicated_lines_density", "value": "0.0", "bestValue": true}, {"metric": "functions", "value": "4"}, {"metric": "security_rating", "value": "1.0", "bestValue": true}, {"metric": "files", "value": "3"}, {"metric": "complexity", "value": "5"}, {"metric": "ncloc", "value": "40"}, {"metric": "coverage", "value": "80.8", "bestValue": false}, {"metric": "reliability_rating", "value": "1.0", "bestValue": true}, {"metric": "comment_lines_density", "value": "0.0", "bestValue": false}]}, {"id": "AXhhCSPPVrchjitanYAp", "key": "fga-eps-mds_2020-2-G4-Demands:src", "name": "src", "qualifier": "DIR", "path": "src", "measures": [{"metric": "duplicated_lines_density", "value": "0.0", "bestValue": true}, {"metric": "functions", "value": "57"}, {"metric": "security_rating", "value": "1.0", "bestValue": true}, {"metric": "files", "value": "14"}, {"metric": "complexity", "value": "125"}, {"metric": "ncloc", "value": "1035"}, {"metric": "coverage", "value": "90.3", "bestValue": false}, {"metric": "reliability_rating", "value": "1.0", "bestValue": true}, {"metric": "comment_lines_density", "value": "0.0", "bestValue": false}]}, {"id": "AXkeJgjjaPZPm53PKkdL", "key": "fga-eps-mds_2020-2-G4-Demands:tests/__mocks__", "name": "tests/__mocks__", "qualifier": "DIR", "path": "tests/__mocks__", "measures": [{"metric": "duplicated_lines_density", "value": "0.0", "bestValue": true}, {"metric": "functions", "value": "2"}, {"metric": "security_rating", "value": "1.0", "bestValue": true}, {"metric": "files", "value": "1"}, {"metric": "complexity", "value": "5"}, {"metric": "ncloc", "value": "21"}, {"metric": "reliability_rating", "value": "1.0", "bestValue": true}, {"metric": "comment_lines_density", "value": "0.0", "bestValue": false}]}, {"id": "AXkk61nHGsI8ClE_MzUV", "key": "fga-eps-mds_2020-2-G4-Demands:src/Services/Axios/userService.js", "name": "userService.js", "qualifier": "FIL", "path": "src/Services/Axios/userService.js", "language": "js", "measures": [{"metric": "functions", "value": "2"}, {"metric": "security_rating", "value": "1.0", "bestValue": true}, {"metric": "files", "value": "1"}, {"metric": "complexity", "value": "3"}, {"metric": "ncloc", "value": "14"}, {"metric": "coverage", "value": "75.0", "bestValue": false}, {"metric": "reliability_rating", "value": "1.0", "bestValue": true}, {"metric": "comment_lines_density", "value": "0.0", "bestValue": false}, {"metric": "duplicated_lines_density", "value": "0.0", "bestValue": true}, {"metric": "test_success_density", "value": "100.0", "bestValue": true}]}, {"id": "AXkeJgjjaPZPm53PKkdO", "key": "fga-eps-mds_2020-2-G4-Demands:src/Utils", "name": "Utils", "qualifier": "DIR", "path": "src/Utils", "measures": [{"metric": "duplicated_lines_density", "value": "0.0", "bestValue": true}, {"metric": "functions", "value": "13"}, {"metric": "security_rating", "value": "1.0", "bestValue": true}, {"metric": "files", "value": "3"}, {"metric": "complexity", "value": "45"}, {"metric": "ncloc", "value": "152"}, {"metric": "reliability_rating", "value": "1.0", "bestValue": true}, {"metric": "comment_lines_density", "value": "0.0", "bestValue": false}]}, {"id": "AXkeJgjjaPZPm53PKkdM", "key": "fga-eps-mds_2020-2-G4-Demands:src/Utils/validate.js", "name": "validate.js", "qualifier": "FIL", "path": "src/Utils/validate.js", "language": "js", "measures": [{"metric": "complexity", "value": "28"}, {"metric": "functions", "value": "7"}, {"metric": "ncloc", "value": "87"}, {"metric": "reliability_rating", "value": "1.0", "bestValue": true}, {"metric": "security_rating", "value": "1.0", "bestValue": true}, {"metric": "comment_lines_density", "value": "0.0", "bestValue": false}, {"metric": "files", "value": "1"}, {"metric": "duplicated_lines_density", "value": "0.0", "bestValue": true}, {"metric": "test_success_density", "value": "100.0", "bestValue": true}]}, {"id": "AXkk61nHGsI8ClE_MzUU", "key": "fga-eps-mds_2020-2-G4-Demands:src/Utils/verifyChanges.js", "name": "verifyChanges.js", "qualifier": "FIL", "path": "src/Utils/verifyChanges.js", "language": "js", "measures": [{"metric": "complexity", "value": "13"}, {"metric": "functions", "value": "4"}, {"metric": "ncloc", "value": "49"}, {"metric": "reliability_rating", "value": "1.0", "bestValue": true}, {"metric": "security_rating", "value": "1.0", "bestValue": true}, {"metric": "comment_lines_density", "value": "0.0", "bestValue": false}, {"metric": "files", "value": "1"}, {"metric": "duplicated_lines_density", "value": "0.0", "bestValue": true}, {"metric": "test_success_density", "value": "100.0", "bestValue": true}]}]}